{
    "packaging" : [
        {
            "basic" : "Upload a compressed ZIP archive containing all Perl source code, maintaining the project structure, to Veracode.",
            "sca": [
                "Not Supported."
            ],
            "format" : [
                {
                    "type" : "ZIP",
                    "structure": [],
                    "notes": [
                        {
                            "note": "Do not include third-party packages."  
                        }
                    ]
                }                                           
            ],
            "special" : [
                {
                    "type": "",
                    "notes": [
                        {
                            "note": ""
                        }
                    ]
                } 
            ]
        }
    ],
    "compilation" : [
        {
            "basic" : "",
            "code" : "",
            "notes" : []
       }
    ],
    "reference" : [
        {
            "type" : "links",
            "resource": [
                {
                    "name": "Perl Compilation/Packaging Guide",
                    "url": "https://docs.veracode.com/r/compilation_perl"
                }
            ]
        },
        {
            "type" : "videos",
            "resource": [
                {
                    "name": "Start a Static Scan",
                    "url": "https://www.youtube.com/embed/M-v0dodSavM"
                }
            ]
        },
        {
            "type" : "examples",
            "resource": [
                {
                    "name": "Perl Example",
                    "url": "N/A"
                }
            ]
        }
    ]

}